APasm.py
AvalonPasm.py
APasm_ROOT/OS/main.py
APasm_ROOT/classes/QEMU.py
APasm_ROOT/classes/enev.py
APasm_ROOT/definitions/BIOS.py
APasm_ROOT/definitions/RM.py
APasm_ROOT/definitions/int.py
APasm_ROOT/definitions/mod.py
APasm_ROOT/definitions/modrm.py
APasm_ROOT/definitions/org.py
APasm_ROOT/instruction/adc.py
APasm_ROOT/instruction/add.py
APasm_ROOT/instruction/cli.py
APasm_ROOT/instruction/halt.py
APasm_ROOT/instruction/jmp.py
APasm_ROOT/instruction/mov.py
APasm_ROOT/instruction/ors.py
APasm_ROOT/instruction/preflix.py
APasm_ROOT/instruction/pushpop.py
APasm_ROOT/instruction/sbb.py
APasm_ROOT/utils/fileOut.py
apasm-1.0.16.1.dist-info/licenses/License.md
apasm-1.0.16.1.dist-info/METADATA
apasm-1.0.16.1.dist-info/WHEEL
apasm-1.0.16.1.dist-info/top_level.txt
apasm-1.0.16.1.dist-info/RECORD
