Metadata-Version: 2.4
Name: APasm
Version: 1.0.16.1
Summary: Avalon Python Assembly (APasm) - a library for coding and supporting Assembly in Python
Author: RandomX
License: MIT License
Keywords: assembly,python,binary,apasm
Requires-Python: >=3.8
License-File: License.md
Dynamic: license-file
